calute/__init__.py
calute/basics.py
calute/calute.py
calute/config.py
calute/errors.py
calute/executors.py
calute/logging_config.py
calute/loggings.py
calute/multimodal.py
calute/streamer_buffer.py
calute/utils.py
calute/agents/__init__.py
calute/agents/_coder_agent.py
calute/agents/_data_analyst_agent.py
calute/agents/_planner_agent.py
calute/agents/_researcher_agent.py
calute/agents/auto_compact_agent.py
calute/agents/compaction_agent.py
calute/api_server/__init__.py
calute/api_server/completion_service.py
calute/api_server/converters.py
calute/api_server/cortex_completion_service.py
calute/api_server/models.py
calute/api_server/routers.py
calute/api_server/server.py
calute/context_management/__init__.py
calute/context_management/compaction_strategies.py
calute/context_management/token_counter.py
calute/cortex/__init__.py
calute/cortex/agent.py
calute/cortex/cortex.py
calute/cortex/dynamic.py
calute/cortex/enums.py
calute/cortex/memory_integration.py
calute/cortex/planner.py
calute/cortex/string_utils.py
calute/cortex/task.py
calute/cortex/task_creator.py
calute/cortex/templates.py
calute/cortex/tool.py
calute/cortex/universal_agent.py
calute/llms/__init__.py
calute/llms/anthropic.py
calute/llms/base.py
calute/llms/gemini.py
calute/llms/ollama.py
calute/llms/openai.py
calute/mcp/__init__.py
calute/mcp/client.py
calute/mcp/integration.py
calute/mcp/manager.py
calute/mcp/types.py
calute/memory/__init__.py
calute/memory/base.py
calute/memory/compat.py
calute/memory/contextual_memory.py
calute/memory/entity_memory.py
calute/memory/long_term_memory.py
calute/memory/short_term_memory.py
calute/memory/storage.py
calute/memory/user_memory.py
calute/tools/__init__.py
calute/tools/ai_tools.py
calute/tools/coding_tools.py
calute/tools/data_tools.py
calute/tools/duckduckgo_engine.py
calute/tools/math_tools.py
calute/tools/memory_tool.py
calute/tools/standalone.py
calute/tools/system_tools.py
calute/tools/web_tools.py
calute/types/__init__.py
calute/types/agent_types.py
calute-0.1.5.dist-info/METADATA
calute-0.1.5.dist-info/WHEEL
calute-0.1.5.dist-info/licenses/LICENSE
calute-0.1.5.dist-info/RECORD
