Metadata-Version: 2.4
Name: calute
Version: 0.1.5
Summary: Agents for intelligence and coordination
Project-URL: Homepage, https://github.com/erfanzar/Calute
Project-URL: Repository, https://github.com/erfanzar/Calute
Project-URL: Documentation, https://erfanzar.github.io/Calute
Author-email: Erfan Zare Chavoshi <Erfanzare810@gmail.com>
License: Apache-2.0
License-File: LICENSE
Keywords: AI,Agents,LLM,calute,orchestration
Classifier: Development Status :: 3 - Alpha
Classifier: Intended Audience :: Developers
Classifier: License :: OSI Approved :: Apache Software License
Classifier: Programming Language :: Python :: 3.10
Classifier: Programming Language :: Python :: 3.11
Classifier: Programming Language :: Python :: 3.12
Classifier: Programming Language :: Python :: 3.13
Classifier: Topic :: Scientific/Engineering :: Artificial Intelligence
Requires-Python: <3.14,>=3.10
Requires-Dist: ddgs>=9.5.4
Requires-Dist: fastapi>=0.116.1
Requires-Dist: google-generativeai<0.9.0,>=0.8.0
Requires-Dist: httpx>=0.25.0
Requires-Dist: jinja2>=3.1.6
Requires-Dist: lxml>=5.0.0
Requires-Dist: numpy>=1.24.0
Requires-Dist: openai>=1.72.0
Requires-Dist: pillow>=11.0.0
Requires-Dist: psutil>=5.9.0
Requires-Dist: pydantic<3.0.0,>=2.9.2
Requires-Dist: requests>=2.31.0
Requires-Dist: uvicorn>=0.35.0
Provides-Extra: ai-complete
Requires-Dist: scikit-learn>=1.3.0; extra == 'ai-complete'
Requires-Dist: sentence-transformers>=2.3.0; extra == 'ai-complete'
Provides-Extra: dev
Requires-Dist: black>=24.8.0; extra == 'dev'
Requires-Dist: ipykernel>=6.29.0; extra == 'dev'
Requires-Dist: mypy>=1.12.0; extra == 'dev'
Requires-Dist: notebook>=7.0.0; extra == 'dev'
Requires-Dist: pre-commit>=3.6.0; extra == 'dev'
Requires-Dist: pytest-asyncio>=0.23.0; extra == 'dev'
Requires-Dist: pytest-cov>=4.1.0; extra == 'dev'
Requires-Dist: pytest-mock>=3.12.0; extra == 'dev'
Requires-Dist: pytest>=8.3.3; extra == 'dev'
Requires-Dist: ruff>=0.7.0; extra == 'dev'
Provides-Extra: enterprise
Requires-Dist: datadog>=0.48.0; extra == 'enterprise'
Requires-Dist: opentelemetry-api>=1.22.0; extra == 'enterprise'
Requires-Dist: opentelemetry-instrumentation>=0.43b0; extra == 'enterprise'
Requires-Dist: opentelemetry-sdk>=1.22.0; extra == 'enterprise'
Requires-Dist: prometheus-client>=0.19.0; extra == 'enterprise'
Requires-Dist: psutil>=5.9.0; extra == 'enterprise'
Requires-Dist: sentry-sdk>=1.40.0; extra == 'enterprise'
Requires-Dist: structlog>=24.1.0; extra == 'enterprise'
Provides-Extra: full
Requires-Dist: beautifulsoup4>=4.12.0; extra == 'full'
Requires-Dist: chainlit~=2.9.2; extra == 'full'
Requires-Dist: datadog>=0.48.0; extra == 'full'
Requires-Dist: feedparser>=6.0.0; extra == 'full'
Requires-Dist: markdown>=3.5.0; extra == 'full'
Requires-Dist: mcp>=1.1.0; extra == 'full'
Requires-Dist: opentelemetry-api>=1.22.0; extra == 'full'
Requires-Dist: opentelemetry-instrumentation>=0.43b0; extra == 'full'
Requires-Dist: opentelemetry-sdk>=1.22.0; extra == 'full'
Requires-Dist: prometheus-client>=0.19.0; extra == 'full'
Requires-Dist: psutil>=5.9.0; extra == 'full'
Requires-Dist: python-dateutil>=2.8.0; extra == 'full'
Requires-Dist: pyyaml>=6.0; extra == 'full'
Requires-Dist: scikit-learn>=1.3.0; extra == 'full'
Requires-Dist: sentence-transformers>=2.3.0; extra == 'full'
Requires-Dist: sentry-sdk>=1.40.0; extra == 'full'
Requires-Dist: structlog>=24.1.0; extra == 'full'
Provides-Extra: mcp
Requires-Dist: mcp>=1.1.0; extra == 'mcp'
Provides-Extra: monitoring
Requires-Dist: datadog>=0.48.0; extra == 'monitoring'
Requires-Dist: opentelemetry-api>=1.22.0; extra == 'monitoring'
Requires-Dist: opentelemetry-instrumentation>=0.43b0; extra == 'monitoring'
Requires-Dist: opentelemetry-sdk>=1.22.0; extra == 'monitoring'
Requires-Dist: prometheus-client>=0.19.0; extra == 'monitoring'
Requires-Dist: psutil>=5.9.0; extra == 'monitoring'
Requires-Dist: sentry-sdk>=1.40.0; extra == 'monitoring'
Requires-Dist: structlog>=24.1.0; extra == 'monitoring'
Provides-Extra: research
Requires-Dist: beautifulsoup4>=4.12.0; extra == 'research'
Requires-Dist: chainlit~=2.9.2; extra == 'research'
Requires-Dist: feedparser>=6.0.0; extra == 'research'
Requires-Dist: markdown>=3.5.0; extra == 'research'
Requires-Dist: python-dateutil>=2.8.0; extra == 'research'
Requires-Dist: pyyaml>=6.0; extra == 'research'
Requires-Dist: scikit-learn>=1.3.0; extra == 'research'
Requires-Dist: sentence-transformers>=2.3.0; extra == 'research'
Provides-Extra: search
Requires-Dist: beautifulsoup4>=4.12.0; extra == 'search'
Requires-Dist: feedparser>=6.0.0; extra == 'search'
Requires-Dist: python-dateutil>=2.8.0; extra == 'search'
Requires-Dist: pyyaml>=6.0; extra == 'search'
Provides-Extra: ui
Requires-Dist: chainlit~=2.9.2; extra == 'ui'
Requires-Dist: markdown>=3.5.0; extra == 'ui'
Provides-Extra: vectors
Requires-Dist: scikit-learn>=1.3.0; extra == 'vectors'
Requires-Dist: sentence-transformers>=2.3.0; extra == 'vectors'
